seatease/__init__.py
seatease/cseatease.py
seatease/spectrometers.py
seatease-0.4.0.dist-info/LICENSE
seatease-0.4.0.dist-info/METADATA
seatease-0.4.0.dist-info/WHEEL
seatease-0.4.0.dist-info/top_level.txt
seatease-0.4.0.dist-info/RECORD
