Metadata-Version: 2.1
Name: seatease
Version: 0.4.0
Summary: A software emulator for the `python-seabreeze` package
Home-page: https://github.com/jonathanvanschenck/python-seatease
Author: Jonathan D B Van Schenck
Author-email: vanschej@oregonstate.edu
License: UNKNOWN
Platform: UNKNOWN
Classifier: Programming Language :: Python :: 3
Classifier: License :: OSI Approved :: MIT License
Classifier: Operating System :: OS Independent
Requires-Python: >=3.6
